Workbook

Sheet Read me
B1: Refill: citations and evidence
B2: Team C29 · Fynd x NMIMS Hyderabad Product & Business Simulation · Case C29 Appointment Recovery Desk
B4: What this file is | C4: Every claim Refill makes in the deck, the documents, the film and the guides, with where it came from. Outside facts are on 'Citations'. Claims we prove with our own tests are on 'Product evidence'. Our own estimates are on 'Assumptions'. 'Our numbers' rebuilds the deck's financial table with live formulas.
B5: Sources checked on | C5: 18 Oct 2026. Each link was opened and read; the 'What the source says' column quotes or paraphrases what it said that day.
B6: Live app | C6: https://fillthechair.vercel.app
B7: Repository | C7: https://github.com/sirgreaseball/refill
B9: Status key
B10: Verified | C10: The source says what we say.
B11: Verified with caveat | C11: The source supports the claim, with a limit worth saying aloud (a vendor survey, another country, a secondary report).
B12: Needs correction | C12: The source says something different or the citation points to the wrong place. The note gives the fix.
B13: Not verified | C13: No source found that confirms it.
B14: Passed (observed) | C14: Our own test or check, run on the live system on the date shown.
B15: Demo data (synthetic) | C15: A number from the made-up demo salon. Never presented as real revenue.
B16: Hypothesis | C16: Our assumption, with the test that will confirm or reject it.
B18: Counts
B19: Outside sources (Citations) | C19: =COUNTA(Citations!A2:A200) -> 36
B20: Verified | C20: =COUNTIF(Citations!J2:J200,"Verified") -> 15
B21: Verified with caveat | C21: =COUNTIF(Citations!J2:J200,"Verified with caveat") -> 15
B22: Needs correction | C22: =COUNTIF(Citations!J2:J200,"Needs correction") -> 6
B23: Not verified | C23: =COUNTIF(Citations!J2:J200,"Not verified") -> 0
B24: Product claims with evidence | C24: =COUNTA('Product evidence'!A2:A200) -> 12
B25: Assumptions | C25: =COUNTA(Assumptions!A2:A200) -> 15
B26: Financial table cells that match the deck | C26: =COUNTIF('Our numbers'!F16:F40,"Matches")&" of "&(COUNTIF('Our numbers'!F16:F40,"Matches")+COUNTIF('Our numbers'!F16:F40,"Differs")) -> 19 of 19

Sheet Citations
A1: ID | B1: Claim as we made it | C1: Where we made it | D1: Topic | E1: Source | F1: Publisher / author | G1: Link | H1: Published | I1: What the source says | J1: Status | K1: Note / fix | L1: Accessed
A2: C01 | B2: The brief: fill genuinely available appointment slots and reduce missed sessions without overbooking; show cancellations and waiting-list matches, record consent, rebook, prevent duplicate slot allocation. | C2: Final deck (dark + light) slides 1-2; Product film (youtu.be/5BfsKofkIHw) lines 1-2; the whole product | D2: Case requirement | E2: Use Case Book v3, C29 Appointment Recovery Desk, p. 32 | F2: Fynd x NMIMS Hyderabad (case bank) | G2: https://drive.google.com/file/d/1lHi0dQghhwh15UM8cXO0HWz_uvdSb3Xl/view | H2: 16 Oct 2026 | I2: C29 card: user and end goal, engineering build, MBA assignment, growth experiment, product change, starter data. | J2: Verified | K2: Organiser document, shared on the event Drive. | L2: 18 Oct 2026
A3: C02 | B3: Three scored case checks: a 60-minute request cannot take a 30-minute slot (10 pts); two competing requests give one confirmed booking and one waitlist entry (10 pts); a customer without contact consent is excluded (5 pts). | C3: Final deck (dark + light) slide 4; Product film (youtu.be/5BfsKofkIHw) line 20; the Lab (#/lab) | D3: Case requirement | E3: Use Case Book v3, C29, p. 32, 'Case outcome checks for engineering' | F3: Fynd x NMIMS Hyderabad (case bank) | G3: https://drive.google.com/file/d/1lHi0dQghhwh15UM8cXO0HWz_uvdSb3Xl/view | H3: 16 Oct 2026 | I3: Lists the three checks with 10, 10 and 5 points. | J3: Verified | K3: Our proof for each check is on the Product evidence sheet (E01-E03). | L3: 18 Oct 2026
A4: C03 | B4: Market shocks we prepared for: late cancellation, staff absence, a different service duration, a customer withdrawing consent. | C4: Final deck (dark + light) slides 4-5; docs/SHOCKS.md; MBA Master document 'Market shocks' | D4: Case requirement | E4: Use Case Book v3, C29, p. 32, 'Challenge and edge cases' | F4: Fynd x NMIMS Hyderabad (case bank) | G4: https://drive.google.com/file/d/1lHi0dQghhwh15UM8cXO0HWz_uvdSb3Xl/view | H4: 16 Oct 2026 | I4: Names the same four edge cases. | J4: Verified | L4: 18 Oct 2026
A5: C04 | B5: The negotiated product change is 'add service-duration and staff constraints before outreach'; the growth experiment uses five consenting role players; pricing is a per-location subscription. | C5: Final deck (dark + light) slides 3, 4, 6, 7; MBA Master document sections 8, 11, 12 | D5: Case requirement | E5: Use Case Book v3, C29, p. 32, MBA assignment and product change | F5: Fynd x NMIMS Hyderabad (case bank) | G5: https://drive.google.com/file/d/1lHi0dQghhwh15UM8cXO0HWz_uvdSb3Xl/view | H5: 16 Oct 2026 | I5: 'Test per-location subscription', 'Test opt-in waitlist messages with five consenting role players', 'Add service-duration and staff constraints before outreach'. | J5: Verified | L5: 18 Oct 2026
A6: C05 | B6: The 30-day pilot on one calendar measures filled cancellations, no-show rate and staff correction effort. | C6: Final deck (dark + light) slide 7; Product film (youtu.be/5BfsKofkIHw) line 22; MBA Master document section 13 | D6: Case requirement | E6: Use Case Book v3, C29, p. 32, 'Path to a real pilot' | F6: Fynd x NMIMS Hyderabad (case bank) | G6: https://drive.google.com/file/d/1lHi0dQghhwh15UM8cXO0HWz_uvdSb3Xl/view | H6: 16 Oct 2026 | I6: 'Pilot one calendar; measure filled cancellations, no-show rate and staff correction effort.' | J6: Verified | L6: 18 Oct 2026
A7: C06 | B7: India's beauty-salon market is about USD 12.6 billion (2025). | C7: Financial Projections Brief section 08 | D7: Market size | E7: India Beauty Salon Market Size, Share & Forecast, 2026-2031 | F7: Ken Research | G7: https://www.kenresearch.com/industry-reports/india-beauty-salon-market.md | H7: 2026 (base year 2025) | I7: USD 12,565 million service revenue in 2025; forecast USD 19,773 million by 2031. | J7: Verified with caveat | K7: Research-firm estimate; method not public. Present as indicative. | L7: 18 Oct 2026
A8: C07 | B8: About 3,00,000 salon players in India. | C8: Financial Projections Brief section 08 | D8: Market size | E8: India Beauty Salon Market Size, Share & Forecast, 2026-2031 | F8: Ken Research | G8: https://www.kenresearch.com/industry-reports/india-beauty-salon-market.md | H8: 2026 (base year 2025) | I8: 'Total Number of Players: 300,000'; 'approximately 300,000 operators (2025, India)'. | J8: Verified with caveat | K8: Research-firm estimate. | L8: 18 Oct 2026
A9: C08 | B9: Organised salon outlets in India are above 13,000. | C9: Financial Projections Brief section 08 | D9: Market size | E9: India Salon Market Outlook 2032 | F9: Nexdigm | G9: https://www.nexdigm.com/market-research/report-store/india-salon-market/ | H9: 2026 | I9: 'organized salons crossed 13,000 outlets nationwide'. | J9: Verified with caveat | K9: Nexdigm attributes the figure to 'public industry trackers'. | L9: 18 Oct 2026
A10: C09 | B10: Lakme Salon runs 450+ outlets. | C10: Financial Projections Brief section 08 | D10: Market size | E10: India Beauty Salon Market Size, Share & Forecast, 2026-2031 | F10: Ken Research | G10: https://www.kenresearch.com/industry-reports/india-beauty-salon-market.md | H10: 2026 | I10: 'Lakme Salon operates more than 450 salons across 190 cities (2025, India)'. | J10: Needs correction | K10: The number is right, but the brief cites Inventiva for it. Cite Ken Research instead. | L10: 18 Oct 2026
A11: C10 | B11: Naturals runs 800+ outlets. | C11: Financial Projections Brief section 08 | D11: Market size | E11: India Beauty Salon Market Size, Share & Forecast, 2026-2031 | F11: Ken Research | G11: https://www.kenresearch.com/industry-reports/india-beauty-salon-market.md | H11: 2026 | I11: 'Naturals operates more than 800 outlets (2025, India)'. | J11: Needs correction | K11: The brief cites Inventiva, whose page says 650+ (inventiva.co.in/?p=412093). Cite Ken Research, or say '650-800+ depending on source'. | L11: 18 Oct 2026
A12: C11 | B12: Hair and beauty businesses lose almost 7% of monthly revenue to cancellations. | C12: Financial Projections Brief section 06 | D12: Customer pain | E12: The Hidden Cost of Cancellations: How No-Shows Are Reshaping the Beauty Industry | F12: Fresha | G12: https://www.fresha.com/blog/cancellations-cost-study | H12: 2 Feb 2026 (updated 4 Feb 2026) | I12: 'In hair and beauty, average revenue lost to cancellations sits at almost 7% a month'. | J12: Verified with caveat | K12: A survey of UK businesses by a booking-software vendor. Say 'UK survey' when quoting it. | L12: 18 Oct 2026
A13: C12 | B13: Small-business software commonly loses 3-7% of customers a month. | C13: Financial Projections Brief section 05 | D13: SaaS benchmark | E13: SaaS Churn Rate: What It Is, How to Calculate It, and Benchmarks | F13: Kalungi (Fadi George) | G13: https://kalungi.com/blog/saas-churn-rate-benchmarks | H13: 5 May 2025 | I13: 'For small to medium-sized businesses (SMBs), which typically bill monthly, you'll see a churn rate between 3 and 7%.' | J13: Verified with caveat | K13: Vendor blog benchmark. | L13: 18 Oct 2026
A14: C13 | B14: The same 3-7% monthly churn range, second source. | C14: Financial Projections Brief section 09 (Sources) | D14: SaaS benchmark | E14: SaaS Churn Rate Benchmarks: What's Actually Normal in 2026 | F14: UserJot | G14: https://userjot.com/blog/saas-churn-rate-benchmarks | H14: 2026 | I14: Says 'SMB-focused products: 5-7% annual is realistic' and 'anything over 2-3% monthly is a problem'. | J14: Needs correction | K14: UserJot does not support 3-7% a month. Keep it only for row C14. | L14: 18 Oct 2026
A15: C14 | B15: Much of software churn happens in the first three months. | C15: Financial Projections Brief section 05 | D15: SaaS benchmark | E15: SaaS Churn Rate Benchmarks: What's Actually Normal in 2026 | F15: UserJot | G15: https://userjot.com/blog/saas-churn-rate-benchmarks | H15: 2026 | I15: 'The majority of churn happens in the first 90 days.' | J15: Verified with caveat | K15: Vendor blog. | L15: 18 Oct 2026
A16: C15 | B16: Payment gateway fees are about 2% of the ₹699 subscription. | C16: Financial Projections Brief section 04; MBA Master document section 9 | D16: Cost to serve | E16: Razorpay pricing | F16: Razorpay | G16: https://razorpay.com/pricing/ | H16: Live page | I16: Standard plan fee 2% (new accounts currently get 0% for the first 90 days). | J16: Verified | L16: 18 Oct 2026
A17: C16 | B17: A WhatsApp utility message costs about ₹0.12-0.15. | C17: Financial Projections Brief section 04; MBA Master document section 9 | D17: Cost to serve | E17: WhatsApp Business API pricing in India (Meta rate card summary) | F17: Whautomate | G17: https://whautomate.com/whatsapp-business-api-pricing-india | H17: Rate card effective 1 Oct 2026 | I17: Utility messages ₹0.115 each; from 1 Oct 2026 also charged inside the service window. Provider fees can add 10-30%. | J17: Verified with caveat | K17: Secondary summary; Meta's own pricing page blocks automated reading. Official page: developers.facebook.com/documentation/business-messaging/whatsapp/pricing | L17: 18 Oct 2026
A18: C17 | B18: An SMS costs about ₹0.15-0.25. | C18: Financial Projections Brief section 04; MBA Master document section 9 | D18: Cost to serve | E18: SMS pricing, India to India | F18: MSG91 | G18: https://msg91.com/in/pricing/sms | H18: Live page | I18: ₹0.16 to ₹0.25 per SMS depending on volume, plus 18% GST. | J18: Verified | K18: Lowest published rate is ₹0.16, not ₹0.15. | L18: 18 Oct 2026
A19: C18 | B19: SMS needs DLT registration and approved templates. | C19: MBA Master document section 15 (risks) | D19: Regulation | E19: Telecom Commercial Communications Customer Preference Regulations, 2018 | F19: Telecom Regulatory Authority of India (TRAI) | G19: https://www.trai.gov.in/sites/default/files/2024-09/RegulationUcc19072018.pdf | H19: 19 Jul 2018 | I19: Defines the Consent Register as a Distributed Ledger and requires content templates to be registered for transactional and service messages. | J19: Verified | L19: 18 Oct 2026
A20: C19 | B20: WhatsApp business messages need approved templates. | C20: MBA Master document section 15 (risks) | D20: Regulation / platform rule | E20: Template fundamentals, WhatsApp Business Platform | F20: Meta for Developers | G20: https://developers.facebook.com/documentation/business-messaging/whatsapp/templates/overview | H20: Live page | I20: Templates must have APPROVED status before they can be sent; outside the 24-hour window only templates can be sent. | J20: Verified with caveat | K20: Confirmed through search results that quote this page; the page itself blocks automated reading. | L20: 18 Oct 2026
A21: C20 | B21: India's Digital Personal Data Protection Act, 2023 requires clear consent. | C21: MBA Master document section 15; consent-first design | D21: Regulation | E21: The Digital Personal Data Protection Bill, 2023 (bill summary) | F21: PRS Legislative Research | G21: https://prsindia.org/billtrack/digital-personal-data-protection-bill-2023 | H21: Aug 2023 | I21: 'Personal data may be processed only for a lawful purpose after obtaining the consent of the individual. A notice must be given before seeking consent.' | J21: Verified | K21: Pinpoint in the Act: section 5 (notice) and section 6 (consent). | L21: 18 Oct 2026
A22: C21 | B22: Supabase Pro costs about US$25 a month. | C22: MBA Master document section 9; Financial Projections Brief section 04 | D22: Cost to serve | E22: Supabase pricing | F22: Supabase | G22: https://supabase.com/pricing | H22: Live page | I22: 'Pro ... From $25 / month'. | J22: Verified | L22: 18 Oct 2026
A23: C22 | B23: Vercel Pro costs about US$20 a month. | C23: MBA Master document section 9; Financial Projections Brief section 04 | D23: Cost to serve | E23: Vercel pricing | F23: Vercel | G23: https://vercel.com/pricing | H23: Live page | I23: 'Pro $20 /mo' with $20 of included usage credit. | J23: Verified | L23: 18 Oct 2026
A24: C23 | B24: Hosting costs are converted at about ₹85 per US$. | C24: MBA Master document section 9 | D24: Cost to serve | E24: USD exchange rates (daily) | F24: ExchangeRate-API | G24: https://open.er-api.com/v6/latest/USD | H24: 18 Oct 2026 | I24: 1 USD = ₹95.08 on 18 Oct 2026. | J24: Needs correction | K24: Use about ₹95. The hosting share for 50 locations rises from about ₹77 to about ₹86 per location a month; the ₹100 COGS still covers it. | L24: 18 Oct 2026
A25: C24 | B25: Mangomint costs $165-$375 a month by team size. | C25: MBA Master document section 7 (competitor table) | D25: Competitor | E25: Mangomint pricing | F25: Mangomint | G25: https://www.mangomint.com/pricing/ | H25: Live page | I25: 'Monthly price is $120 per location and $10 per user', with paid add-ons. | J25: Needs correction | K25: The MBA figure is out of date. Use '$120 per location + $10 per user'. | L25: 18 Oct 2026
A26: C25 | B26: Mangomint handles waitlists with express booking, virtual waiting rooms and automated client flows. | C26: MBA Master document section 7 | D26: Competitor | E26: Mangomint features | F26: Mangomint | G26: https://www.mangomint.com/features/ | H26: Live page | I26: Feature list includes Express Booking, Virtual Waiting Room and Automated Flows. | J26: Verified | L26: 18 Oct 2026
A27: C26 | B27: Vagaro starts at $30 a month for one calendar, more per staff calendar, with waitlist tracking. | C27: MBA Master document section 7 | D27: Competitor | E27: Vagaro pricing | F27: Vagaro | G27: https://www.vagaro.com/pro/pricing | H27: Live page | I27: $30/month for one location ($23.99 introductory); each extra bookable calendar $10, up to seven; 'Customer waitlist options' included. | J27: Verified | L27: 18 Oct 2026
A28: C27 | B28: Fresha has a low base price plus transaction and messaging fees, with waitlists. | C28: MBA Master document section 7; Final deck (dark + light) slide 4 | D28: Competitor | E28: Fresha pricing (India) | F28: Fresha | G28: https://www.fresha.com/pricing | H28: Live page | I28: Free subscription for one person; Team plan charges per bookable team member; texts ₹13.50 and WhatsApp ₹1.60-5.50 after 20 free a month; 'Waitlists' listed as a feature. | J28: Verified with caveat | K28: Payment-processing fees are not shown on this page. | L28: 18 Oct 2026
A29: C28 | B29: Zenoti offers a waitlist. | C29: Final deck (dark + light) slide 4 (gap vs competitors) | D29: Competitor | E29: Zenoti salon software | F29: Zenoti | G29: https://www.zenoti.com/salon-software | H29: Live page | I29: Feature list includes 'Automated Waitlist Management'. | J29: Verified | L29: 18 Oct 2026
A30: C29 | B30: Square offers a waitlist. | C30: Final deck (dark + light) slide 4 (gap vs competitors) | D30: Competitor | E30: Square Appointments features | F30: Square | G30: https://squareup.com/us/en/appointments/features | H30: Live page | I30: 'Create a waitlist for popular services and fill gaps in your schedule due to last-minute cancellations or reschedules.' | J30: Verified | L30: 18 Oct 2026
A31: C30 | B31: Zenoti has its headquarters in Hyderabad. | C31: MBA Master document section 7 | D31: Competitor | E31: Zenoti company page and contact page | F31: Zenoti | G31: https://www.zenoti.com/contact-us | H31: Live page | I31: HQ: 15900 SE Eastgate Way, Bellevue WA, USA. The company page says Zenoti began as ManageMySpa in Hyderabad in 2010. | J31: Needs correction | K31: Say 'founded in Hyderabad, headquartered in Bellevue, USA'. | L31: 18 Oct 2026
A32: C31 | B32: TutorBird costs $16.95 a month solo plus $4.95 per extra tutor, with student waitlists. | C32: MBA Master document section 7 | D32: Competitor | E32: TutorBird pricing | F32: TutorBird | G32: https://www.tutorbird.com/pricing/ | H32: Live page | I32: '$16.95 /month + $4.95 per each additional tutor or staff member'; 'Track your waitlist & leads'. | J32: Verified with caveat | K32: 'Cancelled lessons become make-up slots' is not stated on the pages checked. | L32: 18 Oct 2026
A33: C32 | B33: Calendly and Acuity cost $10-$30+ per seat a month. | C33: MBA Master document section 7 | D33: Competitor | E33: Calendly pricing; Acuity Scheduling plans | F33: Calendly; Squarespace (Acuity) | G33: https://calendly.com/pricing | H33: Live page | I33: Calendly Standard $10/seat/month, Teams $16/seat/month; Acuity Starter $16-$20/month (acuityscheduling.com/signup.php). | J33: Verified with caveat | K33: The top of the range depends on plan; enterprise plans are custom. | L33: 18 Oct 2026
A34: C33 | B34: "Rich people value time": higher-income clients feel short of time, so a relevant opt-in offer of an earlier slot is credible. | C34: Final deck (dark + light) slide 3 (psychographic insight) | D34: Customer insight | E34: Stressed Out on Four Continents: Time Crunch or Yuppie Kvetch? (NBER Working Paper 10186) | F34: Daniel S. Hamermesh and Jungmin Lee | G34: https://www.nber.org/papers/w10186 | H34: 2003; Review of Economics and Statistics, 2007 | I34: 'Time stress will be more prevalent in households with higher incomes'; corroborated in Australia, Canada, Germany, Korea and the US. | J34: Verified with caveat | K34: Research on time stress in general, not on salon clients. | L34: 18 Oct 2026
A35: C34 | B35: People who pay to save time are happier, which supports selling convenience to time-poor clients. | C35: Final deck (dark + light) slide 3 (supporting reading) | D35: Customer insight | E35: Buying time promotes happiness, PNAS 114(32): 8523-8527 | F35: Ashley V. Whillans, Elizabeth W. Dunn, Paul Smeets, Rene Bekkers, Michael I. Norton | G35: https://doi.org/10.1073/pnas.1706541114 | H35: Jul 2017 | I35: Spending on time-saving services was linked to greater life satisfaction across four countries; a field experiment found the same. | J35: Verified with caveat | K35: Supporting evidence only; the deck quotes a team insight, not this paper. | L35: 18 Oct 2026
A36: C35 | B36: A Booksy survey of US salons found only about 2% of clients cancel without any warning. | C36: MBA guide (public/guide/mba.html) | D36: Customer pain | E36: No-Shows: Does Your City Have a High Rate? | F36: Salon Today (reporting a Booksy survey) | G36: https://www.salontoday.com/1076870/no-shows-does-your-city-have-a-high-rate | H36: 23 Sep 2021 | I36: 'at worst over time only about 2 percent of clients don't even give the salon a heads-up'; 15 US cities, 0.98% to 2.37%. | J36: Verified with caveat | K36: 2021 US data, reported second-hand. | L36: 18 Oct 2026
A37: C36 | B37: Treatwell (UK) reports 2-3% no-shows per treatment, and says salons requiring prepayment halved theirs. | C37: MBA guide (public/guide/mba.html) | D37: Customer pain | E37: Beauty salon no-shows: the UK locations with the highest rates | F37: Scratch Magazine (reporting Treatwell research) | G37: https://www.scratchmagazine.co.uk/news/beauty-salon-no-shows-uk-locations-highest-rates/ | H37: Mar 2025 | I37: Highest no-show treatments run 2.69% to 3.14%; '17% of salons now requiring pre-payment, which has reduced no-shows by half'. | J37: Verified with caveat | K37: 2-3% is the range for the most-missed treatments, not every treatment. | L37: 18 Oct 2026

Sheet Product evidence
A1: ID | B1: Claim | C1: Where we made it | D1: Evidence (file, test or page) | E1: Observed result | F1: Status
A2: E01 | B2: A 60-minute request never takes a 30-minute slot. | C2: Final deck (dark + light) slide 4; Product film (youtu.be/5BfsKofkIHw) line 20 | D2: Fit check in src/engine.ts and in the database functions (supabase/migrations); scenario C02 in tests/core-scenarios.json; Lab case check on #/lab. | E2: npm test 51/51 and npm run dbtest 28/28 passed on 18 Oct 2026. | F2: Passed (observed)
A3: E02 | B3: Two requests for one slot give one confirmed booking; the other client keeps their waitlist place. | C3: Final deck (dark + light) slides 4, 7; Product film (youtu.be/5BfsKofkIHw) lines 13-14 | D3: Booking decided inside the database under a row lock plus a unique index; scenarios C04, C09, C13, C14; npm run race (8 simultaneous taps). | E3: npm run race: 3 of 3 runs gave one booking and 7 clients kept their place; a repeated tap returned the same booking (18 Oct 2026). | F3: Passed (observed)
A4: E03 | B4: A customer without contact consent is excluded from outreach, with the reason logged. | C4: Final deck (dark + light) slide 4; Product film (youtu.be/5BfsKofkIHw) line 9 | D4: Scenarios C05, C06, C12; reason code NO_CONSENT in the evidence log. | E4: npm test and npm run dbtest passed on 18 Oct 2026. | F4: Passed (observed)
A5: E04 | B5: Consent is checked when offers go out and again at booking; STOP withdraws every open offer at once. | C5: Final deck (dark + light) slide 4 ('TESTS C05 · C06 · C12'); Product film (youtu.be/5BfsKofkIHw) line 12 | D5: Scenarios C05, C06, C12; race check 'STOP after the offer: booking refused, slot stays free'. | E5: Passed in npm run race and npm run dbtest on 18 Oct 2026. | F5: Passed (observed)
A6: E05 | B6: Offers are held 15 minutes; at most 3 offers per client a day; under-2-hour cancellations are flagged late; no offers inside 10 minutes of the start; mistakes can be undone. | C6: Final deck (dark + light) slides 4-5; Product film (youtu.be/5BfsKofkIHw) line 18 | D6: Database rules OFFER_EXPIRED, FREQUENCY_CAP, late flag and restore_slot (supabase/migrations 002-003); Owner > Rules page. These are defaults the owner can change. | E6: Covered by npm run dbtest (28/28) on 18 Oct 2026. | F6: Passed (observed)
A7: E06 | B7: When staff can't come in, their offers are withdrawn, their gaps held and their clients flagged; the desk moves them or sends a pick-a-time link. | C7: Final deck (dark + light) slides 4-5; Product film (youtu.be/5BfsKofkIHw) line 15 | D7: Staff absence and moves (supabase/migrations 004-005); scenario C20; npm run flowtest. | E7: npm run flowtest 14/14 passed on 18 Oct 2026. | F7: Passed (observed)
A8: E07 | B8: Every cancellation, offer (sent or skipped, with reason), booking, expiry, move and undo is logged and can be exported as CSV or JSON. | C8: Final deck (dark + light) slide 5; Product film (youtu.be/5BfsKofkIHw) line 18 | D8: Append-only events table (migration 003); Activity export in the app. | E8: Visible in the live app; covered by dbtest. | F8: Passed (observed)
A9: E08 | B9: The rules live in the database, not just in the app. | C9: Product film (youtu.be/5BfsKofkIHw) lines 19-20; Final deck (dark + light) slide 7 | D9: Functions-only API: tables have no direct client access; every action is a database function (supabase/migrations). | E9: dbtest calls the live database directly and the rules still hold (28/28). | F9: Passed (observed)
A10: E09 | B10: 51 automated tests, 28 live database checks and 14 cross-role flow checks all pass. | C10: MBA Master document sections 12, 16 | D10: npm test, npm run dbtest, npm run flowtest. | E10: 51/51, 28/28 and 14/14 on 18 Oct 2026. | F10: Passed (observed)
A11: E10 | B11: Demo day: 17 people waiting; 6 fit and 11 are skipped (4 no consent, 2 wrong skill, 2 need more time, 3 not free). | C11: Final deck (dark + light) slide 4 ('6 FIT · 11 SKIPPED'); MBA Master document section 5 | D11: Demo seed for the made-up Kesar Salon (synthetic data, data/salon/*.csv). | E11: Reproduced on the live demo after 'Reset demo day'. | F11: Demo data (synthetic)
A12: E11 | B12: One late cancellation put ₹1,600 at risk and Refill recovered it in two taps. | C12: MBA Master document sections 5, 16; Product film (youtu.be/5BfsKofkIHw) line 16 | D12: Harsh's 12:00 hair spa in the demo seed. | E12: Reproduced on the live demo. | F12: Demo data (synthetic)
A13: E12 | B13: Everything shown runs on synthetic data; no live revenue is claimed. | C13: Product film (youtu.be/5BfsKofkIHw) line 23; Final deck (dark + light); Financial Projections Brief | D13: The case book allows synthetic starter data (Use Case Book p. 1); all figures are tagged 'demo data'. | E13: Checked in the deck, film and brief. | F13: Passed (observed)

Sheet Assumptions
A1: ID | B1: Assumption | C1: Where we used it | D1: Basis | E1: How we test it | F1: Status
A2: A01 | B2: Price ₹699 per location per month is the anchor; test ₹499, ₹699 and ₹999. | C2: Final deck (dark + light) slides 2, 6; Financial Projections Brief | D2: MBA team hypothesis. Only a paid-pilot decision counts as validation. | E2: Owner discovery interviews and the paid pilot. | F2: Hypothesis
A3: A02 | B3: MBA Master section 8 tests ₹999 / ₹1,499 / ₹1,999 (H1: ₹1,499). | C3: MBA Master document section 8 | D3: Earlier MBA hypothesis. | E3: Inconsistent with the deck's ₹699 anchor. Align the document with the deck before submitting. | F3: Hypothesis
A4: A03 | B4: Cost to serve is ₹100 per location per month (hosting, messages, payment fees). | C4: Final deck (dark + light) slide 7; Financial Projections Brief section 04 | D4: Built from rows C15-C17 and C21-C22; see the 'Our numbers' sheet. | E4: Real invoices once paid plans start. | F4: Hypothesis
A5: A04 | B5: Average active locations: 50, 250 and 800 in years 1-3. | C5: Final deck (dark + light) slide 7; Financial Projections Brief section 03 | D5: Bottom-up: about 8, 25 and 65 net new locations a month. | E5: The 30-day pilot and the first sales months. | F5: Hypothesis
A6: A05 | B6: Operating costs: ₹15 L, ₹27 L and ₹49 L in years 1-3. | C6: Final deck (dark + light) slide 7; Financial Projections Brief section 05 | D6: Illustrative split: team, sales, marketing, tools, compliance. | E6: Budget review once the team is hired. | F6: Hypothesis
A7: A06 | B7: At ₹500 contribution per service, about 2 recovered bookings a month cover ₹699. | C7: Final deck (dark + light) slide 6 | D7: ₹500 contribution per service is an assumption. | E7: Owner baseline in pilot week 3. | F7: Hypothesis
A8: A07 | B8: Worked example: a salon taking ₹3,00,000 a month loses about ₹21,000 to cancellations. | C8: Financial Projections Brief section 06 | D8: Revenue is an assumption; the 7% comes from row C11 (UK survey). | E8: Owner baseline in pilot week 3. | F8: Hypothesis
A9: A08 | B9: Target customer: owner-operated, one location, 3-15 staff, Hyderabad first. | C9: Final deck (dark + light) slide 3 | D9: Segmentation hypothesis. | E9: Owner interviews and the pilot. | F9: Hypothesis
A10: A09 | B10: Competitors do not expose auditable consent state, duration-mismatch rejection or slot-contention proof to the operator. | C10: Final deck (dark + light) slide 4 | D10: Our reading of competitor product pages; the deck itself says 'Validate by demo before claiming'. | E10: Hands-on demos of Fresha, Zenoti and Square. | F10: Hypothesis
A11: A10 | B11: Calendly and Acuity have weak or no automatic waitlist backfill. | C11: MBA Master document section 7 | D11: Our reading of their product pages; absence is hard to prove. | E11: Hands-on trial of both. | F11: Hypothesis
A12: A11 | B12: Role-player success: at least 3 of 5 respond within the 15-minute hold; at least 4 of 5 rate the offer 4 or 5 for clarity. | C12: MBA Master document section 11 | D12: Targets we set before the test. | E12: The five-role-player experiment. | F12: Hypothesis
... A16: A15 | B16: A 20% salon no-show rate is widely repeated. | C16: MBA guide (public/guide/mba.html) | D16: Flagged in the guide as unverified; it is not used in the deck. | E16: Do not quote it. | F16: Hypothesis

Sheet Our numbers
A1: The financial projections, rebuilt with formulas
A2: Blue cells are inputs (hypotheses, see 'Assumptions'). Black cells are formulas. Column E is what the deck shows; column F checks it.
A4: Inputs | B4: Value | C4: Row ref
A5: Price per location per month (₹) | B5: 699 | C5: A01
A6: Cost to serve per location per month (₹) | B6: 100 | C6: A03
A7: Months in a year | B7: 12
A8: Rupees in one lakh | B8: 100000
A9: Contribution per service (₹) | B9: 500 | C9: A06
A10: Salon revenue in the worked example (₹ / month) | B10: 300000 | C10: A07
A11: Revenue lost to cancellations (hair and beauty) | B11: 0.07 | C11: C11
A12: All salon players in India | B12: 300000 | C12: C07
A13: Organised salon outlets | B13: 13000 | C13: C08
A15: Projection (₹ lakh) | B15: Year 1 | C15: Year 2 | D15: Year 3 | E15: Deck (Y1 | Y2 | Y3) | F15: Check
A16: Average active locations | B16: 50 | C16: 250 | D16: 800 | E16: 50 | 250 | 800 | F16: =IF(AND(ROUND(B16,2)=50,ROUND(C16,2)=250,ROUND(D16,2)=800),"Matches","Differs") -> Matches
A17: Revenue | B17: =B16*$B$5*$B$7/$B$8 -> 4.194 | C17: =C16*$B$5*$B$7/$B$8 -> 20.97 | D17: =D16*$B$5*$B$7/$B$8 -> 67.104 | E17: 4.19 | 20.97 | 67.10 | F17: =IF(AND(ROUND(B17,2)=4.19,ROUND(C17,2)=20.97,ROUND(D17,2)=67.1),"Matches","Differs") -> Matches
A18: Variable COGS | B18: =B16*$B$6*$B$7/$B$8 -> 0.6 | C18: =C16*$B$6*$B$7/$B$8 -> 3 | D18: =D16*$B$6*$B$7/$B$8 -> 9.6 | E18: 0.60 | 3.00 | 9.60 | F18: =IF(AND(ROUND(B18,2)=0.6,ROUND(C18,2)=3,ROUND(D18,2)=9.6),"Matches","Differs") -> Matches
A19: Gross profit | B19: =B17-B18 -> 3.594 | C19: =C17-C18 -> 17.97 | D19: =D17-D18 -> 57.504 | E19: 3.59 | 17.97 | 57.50 | F19: =IF(AND(ROUND(B19,2)=3.59,ROUND(C19,2)=17.97,ROUND(D19,2)=57.5),"Matches","Differs") -> Matches
A20: Total OpEx | B20: 15 | C20: 27 | D20: 49 | E20: 15.00 | 27.00 | 49.00 | F20: =IF(AND(ROUND(B20,2)=15,ROUND(C20,2)=27,ROUND(D20,2)=49),"Matches","Differs") -> Matches
A21: EBITDA | B21: =B19-B20 -> -11.406 | C21: =C19-C20 -> -9.03 | D21: =D19-D20 -> 8.504 | E21: -11.41 | -9.03 | 8.50 | F21: =IF(AND(ROUND(B21,2)=-11.41,ROUND(C21,2)=-9.03,ROUND(D21,2)=8.5),"Matches","Differs") -> Matches
A23: Unit economics and checks | B23: Value | E23: Deck / brief says | F23: Check
A24: Contribution per location per month (₹) | B24: =B5-B6 -> 599 | E24: 599 | F24: =IF(B24=599,"Matches","Differs") -> Matches
A25: Gross margin | B25: =(B5-B6)/B5 -> 0.85693848 | E25: about 86% | F25: =IF(ROUND(B25,2)=0.86,"Matches","Differs") -> Matches
A26: Break-even locations, year 1 OpEx | B26: =ROUNDUP(B20*$B$8/((B5-B6)*B7),0) -> 209 | E26: 209 | F26: =IF(B26=209,"Matches","Differs") -> Matches
A27: Break-even locations, year 3 OpEx | B27: =ROUNDUP(D20*$B$8/((B5-B6)*B7),0) -> 682 | E27: 682 | F27: =IF(B27=682,"Matches","Differs") -> Matches
A28: Break-even at ₹499, year 3 OpEx | B28: =ROUNDUP(D20*$B$8/((499-B6)*B7),0) -> 1024 | E28: about 1,000 | F28: =IF(ABS(B28-1000)<=50,"Matches","Differs") -> Matches
A29: Break-even at ₹999, year 3 OpEx | B29: =ROUNDUP(D20*$B$8/((999-B6)*B7),0) -> 455 | E29: about 450 | F29: =IF(ABS(B29-450)<=10,"Matches","Differs") -> Matches
A30: Recovered bookings a month to cover the price | B30: =B5/B9 -> 1.398 | E30: about 2 | F30: =IF(ROUNDUP(B30,0)=2,"Matches","Differs") -> Matches
A31: Worked example: lost to cancellations (₹ / month) | B31: =B10*B11 -> 21000 | E31: about ₹21,000 | F31: =IF(ROUND(B31,0)=21000,"Matches","Differs") -> Matches
A32: Recovering one-sixth of that, as a multiple of the price | B32: =B10*B11/6/B5 -> 5.0071531 | E32: five times | F32: =IF(ROUND(B32,0)=5,"Matches","Differs") -> Matches
A33: 800 locations as a share of all players | B33: =D16/B12 -> 0.0026666667 | E33: under 0.3% | F33: =IF(B33<0.003,"Matches","Differs") -> Matches
A34: 800 locations as a share of organised outlets | B34: =D16/B13 -> 0.061538462 | E34: about 6% | F34: =IF(ROUND(B34,2)=0.06,"Matches","Differs") -> Matches
A35: 30% slower adoption, year 1 locations | B35: =ROUND(B16*0.7,0) -> 35 | E35: 35 | F35: =IF(B35=35,"Matches","Differs") -> Matches
A36: 30% slower adoption, year 3 locations | B36: =ROUND(D16*0.7,0) -> 560 | E36: 560 | F36: =IF(B36=560,"Matches","Differs") -> Matches
